LICENSE
MANIFEST.in
setup.cfg
setup.py
archipel/__init__.py
archipel/archipelHypervisor.py
archipel/archipelLibvirtEntity.py
archipel/archipelVirtualMachine.py
archipel/libvirtEventLoop.py
archipel_agent.egg-info/PKG-INFO
archipel_agent.egg-info/SOURCES.txt
archipel_agent.egg-info/dependency_links.txt
archipel_agent.egg-info/entry_points.txt
archipel_agent.egg-info/not-zip-safe
archipel_agent.egg-info/requires.txt
archipel_agent.egg-info/top_level.txt
install/bin/archipel-adminaccounts
install/bin/archipel-command
install/bin/archipel-commandsbytag
install/bin/archipel-importvirtualmachine
install/bin/archipel-initinstall
install/bin/archipel-rolesnode
install/bin/archipel-tagnode
install/bin/archipel-testxmppserver
install/bin/archipel-updatedomain
install/bin/runarchipel
install/etc/archipel/archipel.conf
install/etc/archipel/vnc.pem
install/etc/init.d/archipel
install/var/lib/archipel/names.txt
install/var/lib/archipel/avatars/avatar-1.png
install/var/lib/archipel/avatars/avatar-10.png
install/var/lib/archipel/avatars/avatar-11.png
install/var/lib/archipel/avatars/avatar-12.png
install/var/lib/archipel/avatars/avatar-13.png
install/var/lib/archipel/avatars/avatar-14.png
install/var/lib/archipel/avatars/avatar-15.png
install/var/lib/archipel/avatars/avatar-16.png
install/var/lib/archipel/avatars/avatar-17.png
install/var/lib/archipel/avatars/avatar-18.png
install/var/lib/archipel/avatars/avatar-2.png
install/var/lib/archipel/avatars/avatar-3.png
install/var/lib/archipel/avatars/avatar-4.png
install/var/lib/archipel/avatars/avatar-5.png
install/var/lib/archipel/avatars/avatar-6.png
install/var/lib/archipel/avatars/avatar-7.png
install/var/lib/archipel/avatars/avatar-8.png
install/var/lib/archipel/avatars/avatar-9.png
install/var/lib/archipel/avatars/defaulthypervisor.png
install/var/lib/archipel/avatars/defaultvm.png