Metadata-Version: 1.1
Name: archipel-agent
Version: 0.6.0beta
Summary: The hypervisor's agent part of Archipel
Home-page: http://archipelproject.org
Author: Antoine Mercadal
Author-email: primalmotion@archipelproject.org
License: AGPLv3
Keywords: archipel,virtualization,libvirt,orchestration
Platform: UNKNOWN
Classifier: Development Status :: 4 - Beta
Classifier: Environment :: Console
Classifier: Environment :: No Input/Output (Daemon)
Classifier: Intended Audience :: Developers
Classifier: Intended Audience :: Education
Classifier: Intended Audience :: End Users/Desktop
Classifier: Intended Audience :: Science/Research
Classifier: Intended Audience :: System Administrators
Classifier: Intended Audience :: Telecommunications Industry
Classifier: License :: OSI Approved :: GNU Affero General Public License v3
Classifier: Operating System :: POSIX :: Linux
Classifier: Programming Language :: Python
Classifier: Topic :: Internet
Classifier: Topic :: System :: Emulators
Classifier: Topic :: System :: Operating System
Provides: archipel
